{
"type": "FeatureCollection",
"crs": { "type": "name", "properties": { "name": "urn:ogc:def:crs:EPSG::2229" } },
"features": [
{ "type": "Feature", "properties": { }, "geometry": { "type": "Point", "coordinates": [ 6505180.047784606926143, 1882108.044374197721481 ] } },
{ "type": "Feature", "properties": { }, "geometry": { "type": "Point", "coordinates": [ 6505116.541470098309219, 1882167.581544050015509 ] } },
{ "type": "Feature", "properties": { }, "geometry": { "type": "Point", "coordinates": [ 6505148.294627352617681, 1882151.704965422628447 ] } },
{ "type": "Feature", "properties": { }, "geometry": { "type": "Point", "coordinates": [ 6505136.387193381786346, 1882167.581544050015509 ] } },
{ "type": "Feature", "properties": { }, "geometry": { "type": "Point", "coordinates": [ 6505180.047784606926143, 1882165.59697172162123 ] } },
{ "type": "Feature", "properties": { }, "geometry": { "type": "Point", "coordinates": [ 6505277.291828699409962, 1882048.507204345194623 ] } },
{ "type": "Feature", "properties": { }, "geometry": { "type": "Point", "coordinates": [ 6505233.631237474270165, 1882076.291216942947358 ] } },
{ "type": "Feature", "properties": { }, "geometry": { "type": "Point", "coordinates": [ 6505412.242747031152248, 1881800.435663293581456 ] } },
{ "type": "Feature", "properties": { }, "geometry": { "type": "Point", "coordinates": [ 6505495.594784825108945, 1881667.469317290000618 ] } },
{ "type": "Feature", "properties": { }, "geometry": { "type": "Point", "coordinates": [ 6505376.52044512052089, 1881941.340298610972241 ] } },
{ "type": "Feature", "properties": { }, "geometry": { "type": "Point", "coordinates": [ 6505255.461533087305725, 1882112.013518854510039 ] } },
{ "type": "Feature", "properties": { }, "geometry": { "type": "Point", "coordinates": [ 6505449.949621271342039, 1881699.22247454454191 ] } },
{ "type": "Feature", "properties": { }, "geometry": { "type": "Point", "coordinates": [ 6505489.641067839227617, 1881703.191619201330468 ] } },
{ "type": "Feature", "properties": { }, "geometry": { "type": "Point", "coordinates": [ 6505398.350740732625127, 1881695.253329887753353 ] } },
{ "type": "Feature", "properties": { }, "geometry": { "type": "Point", "coordinates": [ 6505338.813570880331099, 1881953.247732581337914 ] } },
{ "type": "Feature", "properties": { }, "geometry": { "type": "Point", "coordinates": [ 6505273.322684043087065, 1882161.627827064832672 ] } },
{ "type": "Feature", "properties": { }, "geometry": { "type": "Point", "coordinates": [ 6505275.307256370782852, 1882096.136940227122977 ] } },
{ "type": "Feature", "properties": { }, "geometry": { "type": "Point", "coordinates": [ 6505598.79254590254277, 1881877.833984101656824 ] } },
{ "type": "Feature", "properties": { }, "geometry": { "type": "Point", "coordinates": [ 6505255.461533087305725, 1882161.627827064832672 ] } },
{ "type": "Feature", "properties": { }, "geometry": { "type": "Point", "coordinates": [ 6505305.075841297395527, 1882149.720393094234169 ] } },
{ "type": "Feature", "properties": { }, "geometry": { "type": "Point", "coordinates": [ 6505287.214690341614187, 1882141.782103780657053 ] } },
{ "type": "Feature", "properties": { }, "geometry": { "type": "Point", "coordinates": [ 6505398.350740732625127, 1882165.59697172162123 ] } },
{ "type": "Feature", "properties": { }, "geometry": { "type": "Point", "coordinates": [ 6505499.563929481431842, 1882086.214078585151583 ] } },
{ "type": "Feature", "properties": { }, "geometry": { "type": "Point", "coordinates": [ 6505463.841627569869161, 1881665.484744961606339 ] } },
{ "type": "Feature", "properties": { }, "geometry": { "type": "Point", "coordinates": [ 6505440.026759629137814, 1881951.263160252943635 ] } },
{ "type": "Feature", "properties": { }, "geometry": { "type": "Point", "coordinates": [ 6505303.091268968768418, 1882074.306644614553079 ] } },
{ "type": "Feature", "properties": { }, "geometry": { "type": "Point", "coordinates": [ 6505368.582155806943774, 1882034.615198046434671 ] } },
{ "type": "Feature", "properties": { }, "geometry": { "type": "Point", "coordinates": [ 6505596.80797357391566, 1881985.000889836112037 ] } },
{ "type": "Feature", "properties": { }, "geometry": { "type": "Point", "coordinates": [ 6505453.918765928596258, 1882032.630625717807561 ] } },
{ "type": "Feature", "properties": { }, "geometry": { "type": "Point", "coordinates": [ 6505445.980476615019143, 1882004.846613120054826 ] } },
{ "type": "Feature", "properties": { }, "geometry": { "type": "Point", "coordinates": [ 6505372.551300463266671, 1881856.003688489086926 ] } },
{ "type": "Feature", "properties": { }, "geometry": { "type": "Point", "coordinates": [ 6505410.258174703456461, 1881865.926550131291151 ] } },
{ "type": "Feature", "properties": { }, "geometry": { "type": "Point", "coordinates": [ 6505386.443306761793792, 1881842.111682190326974 ] } },
{ "type": "Feature", "properties": { }, "geometry": { "type": "Point", "coordinates": [ 6505612.684552201069891, 1881907.602569027803838 ] } },
{ "type": "Feature", "properties": { }, "geometry": { "type": "Point", "coordinates": [ 6505549.178237692452967, 1881979.04717285069637 ] } },
{ "type": "Feature", "properties": { }, "geometry": { "type": "Point", "coordinates": [ 6505509.486791123636067, 1881758.759644396835938 ] } },
{ "type": "Feature", "properties": { }, "geometry": { "type": "Point", "coordinates": [ 6505442.011331957764924, 1881973.093455865513533 ] } },
{ "type": "Feature", "properties": { }, "geometry": { "type": "Point", "coordinates": [ 6505515.440508108586073, 1881713.114480843534693 ] } },
{ "type": "Feature", "properties": { }, "geometry": { "type": "Point", "coordinates": [ 6505455.903338256292045, 1882076.291216942947358 ] } },
{ "type": "Feature", "properties": { }, "geometry": { "type": "Point", "coordinates": [ 6505592.838828917592764, 1882044.538059688406065 ] } },
{ "type": "Feature", "properties": { }, "geometry": { "type": "Point", "coordinates": [ 6505557.116527006030083, 1882115.982663511298597 ] } },
{ "type": "Feature", "properties": { }, "geometry": { "type": "Point", "coordinates": [ 6505563.070243990980089, 1881213.002254083519801 ] } },
{ "type": "Feature", "properties": { }, "geometry": { "type": "Point", "coordinates": [ 6505584.900539603084326, 1881218.955971068702638 ] } },
{ "type": "Feature", "properties": { }, "geometry": { "type": "Point", "coordinates": [ 6505380.489589776843786, 1881659.531027976423502 ] } },
{ "type": "Feature", "properties": { }, "geometry": { "type": "Point", "coordinates": [ 6505521.394225094467402, 1881568.240700869355351 ] } },
{ "type": "Feature", "properties": { }, "geometry": { "type": "Point", "coordinates": [ 6505479.718206197954714, 1881609.916719766100869 ] } },
{ "type": "Feature", "properties": { }, "geometry": { "type": "Point", "coordinates": [ 6505368.582155806943774, 1881177.27995217195712 ] } },
{ "type": "Feature", "properties": { }, "geometry": { "type": "Point", "coordinates": [ 6505499.563929481431842, 1881554.348694570362568 ] } },
{ "type": "Feature", "properties": { }, "geometry": { "type": "Point", "coordinates": [ 6505567.039388648234308, 1881298.338864205172285 ] } },
{ "type": "Feature", "properties": { }, "geometry": { "type": "Point", "coordinates": [ 6505541.239948378875852, 1881302.308008861960843 ] } },
{ "type": "Feature", "properties": { }, "geometry": { "type": "Point", "coordinates": [ 6505533.301659064367414, 1881435.274354865774512 ] } },
{ "type": "Feature", "properties": { }, "geometry": { "type": "Point", "coordinates": [ 6505572.993105633184314, 1881280.477713249390945 ] } },
{ "type": "Feature", "properties": { }, "geometry": { "type": "Point", "coordinates": [ 6505505.51764646731317, 1881532.51839895779267 ] } },
{ "type": "Feature", "properties": { }, "geometry": { "type": "Point", "coordinates": [ 6505414.227319359779358, 1881421.382348566781729 ] } },
{ "type": "Feature", "properties": { }, "geometry": { "type": "Point", "coordinates": [ 6505477.733633869327605, 1881627.777870721649379 ] } },
{ "type": "Feature", "properties": { }, "geometry": { "type": "Point", "coordinates": [ 6505557.116527006030083, 1881371.768040356459096 ] } },
{ "type": "Feature", "properties": { }, "geometry": { "type": "Point", "coordinates": [ 6505511.471363452263176, 1881592.055568810319528 ] } },
{ "type": "Feature", "properties": { }, "geometry": { "type": "Point", "coordinates": [ 6505545.209093035198748, 1881512.672675673849881 ] } },
{ "type": "Feature", "properties": { }, "geometry": { "type": "Point", "coordinates": [ 6505555.131954677402973, 1881469.012084448710084 ] } },
{ "type": "Feature", "properties": { }, "geometry": { "type": "Point", "coordinates": [ 6505483.687350854277611, 1881592.055568810319528 ] } },
{ "type": "Feature", "properties": { }, "geometry": { "type": "Point", "coordinates": [ 6505549.178237692452967, 1881280.477713249390945 ] } },
{ "type": "Feature", "properties": { }, "geometry": { "type": "Point", "coordinates": [ 6505563.070243990980089, 1881320.169159817742184 ] } },
{ "type": "Feature", "properties": { }, "geometry": { "type": "Point", "coordinates": [ 6505535.286231392994523, 1881326.12287680292502 ] } },
{ "type": "Feature", "properties": { }, "geometry": { "type": "Point", "coordinates": [ 6505596.80797357391566, 1881181.249096828745678 ] } },
{ "type": "Feature", "properties": { }, "geometry": { "type": "Point", "coordinates": [ 6505493.610212496481836, 1881635.716160035459325 ] } },
{ "type": "Feature", "properties": { }, "geometry": { "type": "Point", "coordinates": [ 6505513.455935780890286, 1881516.641820330638438 ] } },
{ "type": "Feature", "properties": { }, "geometry": { "type": "Point", "coordinates": [ 6505493.610212496481836, 1881574.194417854538187 ] } },
{ "type": "Feature", "properties": { }, "geometry": { "type": "Point", "coordinates": [ 6505559.10109933372587, 1881391.613763640634716 ] } },
{ "type": "Feature", "properties": { }, "geometry": { "type": "Point", "coordinates": [ 6505525.363369750790298, 1881476.950373762287199 ] } },
{ "type": "Feature", "properties": { }, "geometry": { "type": "Point", "coordinates": [ 6505563.070243990980089, 1881415.428631581598893 ] } },
{ "type": "Feature", "properties": { }, "geometry": { "type": "Point", "coordinates": [ 6505561.085671662352979, 1881435.274354865774512 ] } },
{ "type": "Feature", "properties": { }, "geometry": { "type": "Point", "coordinates": [ 6505531.317086736671627, 1881455.120078149717301 ] } },
{ "type": "Feature", "properties": { }, "geometry": { "type": "Point", "coordinates": [ 6505549.178237692452967, 1881490.842380061279982 ] } },
{ "type": "Feature", "properties": { }, "geometry": { "type": "Point", "coordinates": [ 6505517.425080437213182, 1881496.796097046462819 ] } },
{ "type": "Feature", "properties": { }, "geometry": { "type": "Point", "coordinates": [ 6505386.443306761793792, 1881536.487543614814058 ] } },
{ "type": "Feature", "properties": { }, "geometry": { "type": "Point", "coordinates": [ 6505525.363369750790298, 1881363.829751042881981 ] } },
{ "type": "Feature", "properties": { }, "geometry": { "type": "Point", "coordinates": [ 6505376.52044512052089, 1881615.870436751283705 ] } },
{ "type": "Feature", "properties": { }, "geometry": { "type": "Point", "coordinates": [ 6505285.230118012987077, 1881552.364122241968289 ] } },
{ "type": "Feature", "properties": { }, "geometry": { "type": "Point", "coordinates": [ 6505527.347942079417408, 1881605.94757510907948 ] } },
{ "type": "Feature", "properties": { }, "geometry": { "type": "Point", "coordinates": [ 6505551.162810020148754, 1881246.739983666455373 ] } },
{ "type": "Feature", "properties": { }, "geometry": { "type": "Point", "coordinates": [ 6505622.607413843274117, 1881226.894260382279754 ] } },
{ "type": "Feature", "properties": { }, "geometry": { "type": "Point", "coordinates": [ 6505414.227319359779358, 1881594.040141138713807 ] } },
{ "type": "Feature", "properties": { }, "geometry": { "type": "Point", "coordinates": [ 6505457.887910584919155, 1881590.070996481925249 ] } },
{ "type": "Feature", "properties": { }, "geometry": { "type": "Point", "coordinates": [ 6505467.81077222712338, 1881476.950373762287199 ] } },
{ "type": "Feature", "properties": { }, "geometry": { "type": "Point", "coordinates": [ 6505586.885111931711435, 1881621.824153736466542 ] } },
{ "type": "Feature", "properties": { }, "geometry": { "type": "Point", "coordinates": [ 6505422.165608673356473, 1881203.079392441315576 ] } },
{ "type": "Feature", "properties": { }, "geometry": { "type": "Point", "coordinates": [ 6505424.150181001983583, 1881167.357090529985726 ] } },
{ "type": "Feature", "properties": { }, "geometry": { "type": "Point", "coordinates": [ 6505400.335313061252236, 1881254.678272980032489 ] } },
{ "type": "Feature", "properties": { }, "geometry": { "type": "Point", "coordinates": [ 6505424.150181001983583, 1881461.073795135132968 ] } },
{ "type": "Feature", "properties": { }, "geometry": { "type": "Point", "coordinates": [ 6505557.116527006030083, 1881592.055568810319528 ] } },
{ "type": "Feature", "properties": { }, "geometry": { "type": "Point", "coordinates": [ 6505426.134753330610693, 1881554.348694570362568 ] } },
{ "type": "Feature", "properties": { }, "geometry": { "type": "Point", "coordinates": [ 6505477.733633869327605, 1881381.69090199843049 ] } },
{ "type": "Feature", "properties": { }, "geometry": { "type": "Point", "coordinates": [ 6505582.915967275388539, 1881383.675474326824769 ] } },
{ "type": "Feature", "properties": { }, "geometry": { "type": "Point", "coordinates": [ 6505604.746262887492776, 1881649.608166334219277 ] } },
{ "type": "Feature", "properties": { }, "geometry": { "type": "Point", "coordinates": [ 6505489.641067839227617, 1881167.357090529985726 ] } },
{ "type": "Feature", "properties": { }, "geometry": { "type": "Point", "coordinates": [ 6505451.934193599969149, 1881514.65724800224416 ] } },
{ "type": "Feature", "properties": { }, "geometry": { "type": "Point", "coordinates": [ 6505447.96504894271493, 1881613.885864422889426 ] } },
{ "type": "Feature", "properties": { }, "geometry": { "type": "Point", "coordinates": [ 6505531.317086736671627, 1881179.264524500351399 ] } },
{ "type": "Feature", "properties": { }, "geometry": { "type": "Point", "coordinates": [ 6505279.276401028037071, 1881512.672675673849881 ] } },
{ "type": "Feature", "properties": { }, "geometry": { "type": "Point", "coordinates": [ 6505418.196464017033577, 1881236.817122024483979 ] } },
{ "type": "Feature", "properties": { }, "geometry": { "type": "Point", "coordinates": [ 6505503.533074138686061, 1881395.582908297423273 ] } },
{ "type": "Feature", "properties": { }, "geometry": { "type": "Point", "coordinates": [ 6505541.239948378875852, 1881645.639021677430719 ] } },
{ "type": "Feature", "properties": { }, "geometry": { "type": "Point", "coordinates": [ 6505453.918765928596258, 1881399.552052954211831 ] } },
{ "type": "Feature", "properties": { }, "geometry": { "type": "Point", "coordinates": [ 6505571.008533304557204, 1880808.149499087128788 ] } },
{ "type": "Feature", "properties": { }, "geometry": { "type": "Point", "coordinates": [ 6505600.777118231169879, 1880710.9054549948778 ] } },
{ "type": "Feature", "properties": { }, "geometry": { "type": "Point", "coordinates": [ 6505521.394225094467402, 1880746.627756906440482 ] } },
{ "type": "Feature", "properties": { }, "geometry": { "type": "Point", "coordinates": [ 6505616.653696858324111, 1881087.974197393516079 ] } },
{ "type": "Feature", "properties": { }, "geometry": { "type": "Point", "coordinates": [ 6505525.363369750790298, 1881072.097618766129017 ] } },
{ "type": "Feature", "properties": { }, "geometry": { "type": "Point", "coordinates": [ 6505447.96504894271493, 1881109.804493005853146 ] } },
{ "type": "Feature", "properties": { }, "geometry": { "type": "Point", "coordinates": [ 6505606.730835216119885, 1881054.236467810347676 ] } },
{ "type": "Feature", "properties": { }, "geometry": { "type": "Point", "coordinates": [ 6505561.085671662352979, 1880780.365486489376053 ] } },
{ "type": "Feature", "properties": { }, "geometry": { "type": "Point", "coordinates": [ 6505608.715407544746995, 1881020.498738227412105 ] } },
{ "type": "Feature", "properties": { }, "geometry": { "type": "Point", "coordinates": [ 6505608.715407544746995, 1881127.665643961634487 ] } },
{ "type": "Feature", "properties": { }, "geometry": { "type": "Point", "coordinates": [ 6505551.162810020148754, 1880667.244863769970834 ] } },
{ "type": "Feature", "properties": { }, "geometry": { "type": "Point", "coordinates": [ 6505580.931394946761429, 1880891.501536880619824 ] } },
{ "type": "Feature", "properties": { }, "geometry": { "type": "Point", "coordinates": [ 6505582.915967275388539, 1881127.665643961634487 ] } },
{ "type": "Feature", "properties": { }, "geometry": { "type": "Point", "coordinates": [ 6505541.239948378875852, 1880647.399140485795215 ] } },
{ "type": "Feature", "properties": { }, "geometry": { "type": "Point", "coordinates": [ 6505418.196464017033577, 1881040.344461511587724 ] } },
{ "type": "Feature", "properties": { }, "geometry": { "type": "Point", "coordinates": [ 6505527.347942079417408, 1881097.897059035487473 ] } },
{ "type": "Feature", "properties": { }, "geometry": { "type": "Point", "coordinates": [ 6505592.838828917592764, 1881087.974197393516079 ] } },
{ "type": "Feature", "properties": { }, "geometry": { "type": "Point", "coordinates": [ 6505473.764489212073386, 1881127.665643961634487 ] } },
{ "type": "Feature", "properties": { }, "geometry": { "type": "Point", "coordinates": [ 6505412.242747031152248, 1880992.71472562965937 ] } },
{ "type": "Feature", "properties": { }, "geometry": { "type": "Point", "coordinates": [ 6505618.63826918695122, 1880673.198580755153671 ] } },
{ "type": "Feature", "properties": { }, "geometry": { "type": "Point", "coordinates": [ 6505517.425080437213182, 1881133.619360946817324 ] } },
{ "type": "Feature", "properties": { }, "geometry": { "type": "Point", "coordinates": [ 6505578.94682261813432, 1881149.495939574204385 ] } },
{ "type": "Feature", "properties": { }, "geometry": { "type": "Point", "coordinates": [ 6505497.579357153736055, 1881040.344461511587724 ] } },
{ "type": "Feature", "properties": { }, "geometry": { "type": "Point", "coordinates": [ 6505582.915967275388539, 1881109.804493005853146 ] } },
{ "type": "Feature", "properties": { }, "geometry": { "type": "Point", "coordinates": [ 6505578.94682261813432, 1880871.655813596444204 ] } },
{ "type": "Feature", "properties": { }, "geometry": { "type": "Point", "coordinates": [ 6505551.162810020148754, 1881149.495939574204385 ] } },
{ "type": "Feature", "properties": { }, "geometry": { "type": "Point", "coordinates": [ 6505408.273602374829352, 1881147.511367245810106 ] } },
{ "type": "Feature", "properties": { }, "geometry": { "type": "Point", "coordinates": [ 6505428.119325659237802, 1881087.974197393516079 ] } },
{ "type": "Feature", "properties": { }, "geometry": { "type": "Point", "coordinates": [ 6505497.579357153736055, 1880700.982593352906406 ] } },
{ "type": "Feature", "properties": { }, "geometry": { "type": "Point", "coordinates": [ 6505622.607413843274117, 1880808.149499087128788 ] } },
{ "type": "Feature", "properties": { }, "geometry": { "type": "Point", "coordinates": [ 6505537.270803721621633, 1880714.874599651899189 ] } },
{ "type": "Feature", "properties": { }, "geometry": { "type": "Point", "coordinates": [ 6505618.63826918695122, 1880883.563247566809878 ] } },
{ "type": "Feature", "properties": { }, "geometry": { "type": "Point", "coordinates": [ 6505610.699979872442782, 1880770.442624847404659 ] } },
{ "type": "Feature", "properties": { }, "geometry": { "type": "Point", "coordinates": [ 6505557.116527006030083, 1880909.362687836168334 ] } },
{ "type": "Feature", "properties": { }, "geometry": { "type": "Point", "coordinates": [ 6505495.594784825108945, 1880423.142467375146225 ] } },
{ "type": "Feature", "properties": { }, "geometry": { "type": "Point", "coordinates": [ 6505499.563929481431842, 1880619.61512788804248 ] } },
{ "type": "Feature", "properties": { }, "geometry": { "type": "Point", "coordinates": [ 6505580.931394946761429, 1880339.79042958188802 ] } },
{ "type": "Feature", "properties": { }, "geometry": { "type": "Point", "coordinates": [ 6505582.915967275388539, 1880419.173322718357667 ] } },
{ "type": "Feature", "properties": { }, "geometry": { "type": "Point", "coordinates": [ 6505594.823401245288551, 1880478.710492570651695 ] } },
{ "type": "Feature", "properties": { }, "geometry": { "type": "Point", "coordinates": [ 6505592.838828917592764, 1880530.309373109368607 ] } }
]
}
